{
    "data" : {
        "updated_on" : "2014-10-01",
        "name"       : "Santos Dumont / Bela Vista",
        "via"        : null,
        "service"    : "regular",
        "trips" : [
            {
                "headsign" : "104 Santos Dumont",
                "shape_id" : null,
                "route"  : []
            },
            {
                "headsign" : "104 Bela Vista",
                "shape_id" : null,
                "route"  : []
            }
        ],
        "timetable" : {
            "weekdays"  : ["06:05", "06:30", "07:00", "07:30", "08:00", "08:35", "09:20", "09:40", "10:10", "10:55",
                           "11:35", "12:15", "12:35", "13:00", "13:35", "14:05", "14:35", "15:05", "15:50", "16:30",
                           "17:15", "18:00", "18:40", "19:00", "19:30"],
            "saturday"  : ["07:00", "07:50", "08:25", "09:10", "09:50", "10:30", "11:10", "11:50", "12:40", "13:50",
                           "15:00", "16:10", "17:10", "19:00"],
            "sunday"    : ["07:00", "08:05", "09:10", "10:15", "11:20", "12:25", "13:30", "14:35", "15:40", "17:35",
                           "18:35"]
        }
    }
}