{
    "data" : {
        "updated_on" : "2014-10-01",
        "name"       : "Bairro do Moscoso / Atlântica Ville",
        "via"        : null,
        "service"    : "regular",
        "trips" : [
            {
                "headsign" : "111 Bairro do Moscoso",
                "shape_id" : null,
                "route"  : []
            },
            {
                "headsign" : "111 Atlântica Ville",
                "shape_id" : null,
                "route"  : []
            }
        ],
        "timetable" : {
            "weekdays"  : ["06:10", "06:35", "06:55", "07:20", "07:40", "07:50", "08:15", "08:35", "09:10", "09:40",
                           "10:30", "11:00", "11:30", "12:00", "12:30", "13:00", "13:30", "14:00", "14:30", "15:00",
                           "15:25", "15:50", "16:20", "16:45", "17:20", "17:50", "18:25", "18:50", "19:50", "20:05",
                           "20:20", "20:40", "21:15", "22:00", "22:50"],
            "saturday"  : ["06:35", "07:05", "07:35", "08:15", "08:45", "10:05", "10:45", "11:25", "12:10", "13:00",
                           "13:45", "14:40", "15:20", "15:50", "16:40", "17:10", "17:45", "19:00", "19:40", "20:20",
                           "21:00", "21:20", "22:00", "22:40"],
            "sunday"    : []
        }
    }
}